README.md
setup.py
elmo/__init__.py
elmo.egg-info/PKG-INFO
elmo.egg-info/SOURCES.txt
elmo.egg-info/dependency_links.txt
elmo.egg-info/requires.txt
elmo.egg-info/top_level.txt
elmo/api/__init__.py
elmo/api/client.py
elmo/api/decorators.py
elmo/api/exceptions.py
elmo/api/router.py
elmo/settings/__init__.py
elmo/settings/base.py
elmo/settings/exceptions.py
elmo/settings/options.py
elmo/settings/validators.py