Metadata-Version: 2.1
Name: elmo
Version: 0.1.2
Summary: API adapter used to control programmatically an Elmo alarm system.
Home-page: https://github.com/palazzem/elmo-alerting
Author: Emanuele Palazzetti
Author-email: hello@palazzetti.me
License: BSD 3-Clause
Platform: UNKNOWN
Classifier: Development Status :: 3 - Alpha
Classifier: Intended Audience :: Developers
Classifier: License :: OSI Approved :: MIT License
Classifier: Programming Language :: Python
Classifier: Programming Language :: Python :: 3
Classifier: Programming Language :: Python :: 3.5
Classifier: Programming Language :: Python :: 3.6
Classifier: Programming Language :: Python :: 3.7
Requires-Python: >=3.5.0
